{
    "Textures": {
        "ArenaConPxz": {
            "size": [4096, 4096],
            "type": "RGB",
            "coordinates": "Genereted",
            "projection": ["Flat", "Cube"],
            "resize": [4.00000, 2.70000, 1.00000],
            "offset": [-0.11100, 0.13900, 0.00000]
        },
        "ArenaFloor": {
            "size": [2048, 2048],
            "type": "RGB",
            "coordinates": "Genereted",
            "projection": ["Flat", "Cube"],
            "resize": [4.00000, 4.00000, 1.00000],
            "offset": [0.00000, 0.00000, 0.00000]
        }
    }
}